{
    "cities": [
        {
            "name": "New York", 
            "currentWeather": "sunny",
            "temperature": 76
        },
        {
            "name": "Miami", 
            "currentWeather": "cloudy",
            "temperature": 62
        },
        {
            "name": "Los Angeles", 
            "currentWeather": "rainy",
            "temperature": 58
        },
        {
            "name": "Chicago", 
            "currentWeather": "snowing",
            "temperature": 30
        },
        {
            "name": "Atlanta", 
            "currentWeather": "thunderstorm",
            "temperature": 40
        }
    ]
}
